{
  "$schema": "http://json-schema.org/draft-07/schema#",
  "type": "object",
  "required": ["$schema", "kind", "name"],
  "properties": {
    "$schema": {
      "const": "manual_schema.json#"
    },
    "$source": {
      "description": "Relative (from arch/) path to the original source file",
      "type": "string",
      "format": "uri-reference"
    },
    "kind": {
      "const": "manual"
    },
    "license": {
      "$ref": "schema_defs.json#/$defs/license"
    },
    "marketing_name": {
      "description": "The publicly displayed manual name",
      "type": "string"
    },
    "name": {
      "description": "Name (database key) of this manual",
      "type": "string"
    },
    "state": {
      "description": "State of this version",
      "$ref": "schema_defs.json#/$defs/spec_state"
    },
    "url": {
      "description": "URL to the repository",
      "type": "string",
      "format": "uri"
    }
  },
  "additionalProperties": false
}
